webdav_tck/__init__.py
webdav_tck/__main__.py
webdav_tck/client.py
webdav_tck/framework/__init__.py
webdav_tck/framework/result.py
webdav_tck/framework/runner.py
webdav_tck/framework/suite.py
webdav_tck/session.py
webdav_tck/suites/__init__.py
webdav_tck/suites/basic.py
webdav_tck/suites/copymove.py
webdav_tck/suites/http.py
webdav_tck/suites/largefile.py
webdav_tck/suites/locks.py
webdav_tck/suites/props.py
webdav_tck/xml_utils.py
webdav_tck-2026.1.1.dist-info/WHEEL
webdav_tck-2026.1.1.dist-info/entry_points.txt
webdav_tck-2026.1.1.dist-info/METADATA
webdav_tck-2026.1.1.dist-info/RECORD
