Metadata-Version: 2.3
Name: webdav-tck
Version: 2026.1.1
Summary: WebDAV server protocol compliance test suite
Keywords: webdav,testing,http,protocol,compliance
Author: webdav_tck contributors
License: GPL-2.0-or-later
Classifier: Development Status :: 3 - Alpha
Classifier: Intended Audience :: Developers
Classifier: License :: OSI Approved :: GNU General Public License v2 or later (GPLv2+)
Classifier: Programming Language :: Python :: 3
Classifier: Programming Language :: Python :: 3.10
Classifier: Programming Language :: Python :: 3.11
Classifier: Programming Language :: Python :: 3.12
Classifier: Topic :: Software Development :: Testing
Classifier: Topic :: Internet :: WWW/HTTP
Requires-Dist: httpx>=0.27.0
Requires-Dist: lxml>=5.0.0
Requires-Dist: click>=8.1.0
Requires-Dist: rich>=13.0.0
Requires-Python: >=3.10
Project-URL: Homepage, https://github.com/abilian/webdav-tck
Project-URL: Issues, https://github.com/abilian/webdav-tck/issues
Project-URL: Repository, https://github.com/abilian/webdav-tck
